MANIFEST.in
README.rst
setup.py
crane_ec2/__init__.py
crane_ec2/models.py
crane_ec2.egg-info/PKG-INFO
crane_ec2.egg-info/SOURCES.txt
crane_ec2.egg-info/dependency_links.txt
crane_ec2.egg-info/requires.txt
crane_ec2.egg-info/top_level.txt