Metadata-Version: 1.0
Name: crane-ec2
Version: 0.1.8
Summary: helper library to service related api actions in ec2 
Home-page: UNKNOWN
Author: timeredbull
Author-email: timeredbull@corp.globo.com
License: UNKNOWN
Platform: UNKNOWN
